win2xcur/__init__.py
win2xcur/cursor.py
win2xcur/main.py
win2xcur/scale.py
win2xcur/shadow.py
win2xcur/theme.py
win2xcur/utils.py
win2xcur/main/__init__.py
win2xcur/main/inspectcur.py
win2xcur/main/win2xcur.py
win2xcur/main/win2xcurtheme.py
win2xcur/main/x2wincur.py
win2xcur/main/x2wincurtheme.py
win2xcur/parser/__init__.py
win2xcur/parser/ani.py
win2xcur/parser/base.py
win2xcur/parser/cur.py
win2xcur/parser/inf.py
win2xcur/parser/xcursor.py
win2xcur/parser/xtheme.py
win2xcur/writer/__init__.py
win2xcur/writer/inf.py
win2xcur/writer/windows.py
win2xcur/writer/x11.py
win2xcur-0.2.0.dist-info/METADATA
win2xcur-0.2.0.dist-info/WHEEL
win2xcur-0.2.0.dist-info/entry_points.txt
win2xcur-0.2.0.dist-info/top_level.txt
win2xcur-0.2.0.dist-info/RECORD
